CHANGES.txt
CONTRIBUTORS.txt
MANIFEST.in
README.txt
setup.py
Products/__init__.py
Products.PFGDataGrid.egg-info/PKG-INFO
Products.PFGDataGrid.egg-info/SOURCES.txt
Products.PFGDataGrid.egg-info/dependency_links.txt
Products.PFGDataGrid.egg-info/entry_points.txt
Products.PFGDataGrid.egg-info/namespace_packages.txt
Products.PFGDataGrid.egg-info/not-zip-safe
Products.PFGDataGrid.egg-info/requires.txt
Products.PFGDataGrid.egg-info/top_level.txt
Products/PFGDataGrid/README.txt
Products/PFGDataGrid/__init__.py
Products/PFGDataGrid/config.py
Products/PFGDataGrid/configure.zcml
Products/PFGDataGrid/setuphandlers.py
Products/PFGDataGrid/vocabulary.py
Products/PFGDataGrid/Extensions/Install.py
Products/PFGDataGrid/Extensions/__init__.py
Products/PFGDataGrid/content/__init__.py
Products/PFGDataGrid/content/datagridff.py
Products/PFGDataGrid/profiles/default/factorytool.xml
Products/PFGDataGrid/profiles/default/import_steps.xml
Products/PFGDataGrid/profiles/default/metadata.xml
Products/PFGDataGrid/profiles/default/pfgdatagrid-various.txt
Products/PFGDataGrid/profiles/default/propertiestool.xml
Products/PFGDataGrid/profiles/default/types.xml
Products/PFGDataGrid/profiles/default/workflows.xml
Products/PFGDataGrid/profiles/default/types/FormDataGridField.xml
Products/PFGDataGrid/tests/__init__.py
Products/PFGDataGrid/tests/base.py
Products/PFGDataGrid/tests/test_doctest.py