Metadata-Version: 1.0
Name: Products.PFGDataGrid
Version: 0.4.1
Summary: Data-grid Field for PloneFormGen
Home-page: http://plone.org/products/ploneformgen
Author: Steve McMahon
Author-email: steve@dcn.org
License: GPL
Keywords: Plone PloneFormGen
Platform: UNKNOWN
Classifier: Framework :: Plone
Classifier: Intended Audience :: Developers
Classifier: Topic :: Software Development :: Libraries :: Python Modules
Classifier: License :: OSI Approved :: GNU General Public License (GPL)
